[
  {
    "played_at": "2026-04-10T04:11:35.461Z",
    "track_id": "6vwVi2dZvyyL0Ld8JtXgFX",
    "track_name": "Bosh (Skit)",
    "artist_id": "4if49KlQEdVNk97CQYSFvt",
    "artist_name": "Pete \u0026 Bas",
    "artist_spotify_url": "https://open.spotify.com/artist/4if49KlQEdVNk97CQYSFvt",
    "album_name": "Mugshot",
    "duration_ms": 30500,
    "track_spotify_url": "https://open.spotify.com/track/6vwVi2dZvyyL0Ld8JtXgFX"
  },
  {
    "played_at": "2026-04-10T01:06:36.524Z",
    "track_id": "4NjAwzMaPdpjiwNUm4q43m",
    "track_name": "Slap the Stick",
    "artist_id": "4if49KlQEdVNk97CQYSFvt",
    "artist_name": "Pete \u0026 Bas",
    "artist_spotify_url": "https://open.spotify.com/artist/4if49KlQEdVNk97CQYSFvt",
    "album_name": "Mugshot",
    "duration_ms": 135667,
    "track_spotify_url": "https://open.spotify.com/track/4NjAwzMaPdpjiwNUm4q43m"
  },
  {
    "played_at": "2026-04-10T01:04:13.246Z",
    "track_id": "5Gj0jCiUc5pWS94vBe0Q49",
    "track_name": "Mugshot Freestyle",
    "artist_id": "4if49KlQEdVNk97CQYSFvt",
    "artist_name": "Pete \u0026 Bas",
    "artist_spotify_url": "https://open.spotify.com/artist/4if49KlQEdVNk97CQYSFvt",
    "album_name": "Mugshot",
    "duration_ms": 146294,
    "track_spotify_url": "https://open.spotify.com/track/5Gj0jCiUc5pWS94vBe0Q49"
  },
  {
    "played_at": "2026-04-10T01:00:13.345Z",
    "track_id": "1LQMedYq9vzeU3hHoij11w",
    "track_name": "Trying to Make It Home",
    "artist_id": "0f8MDDzIc6M4uH1xH0o0gy",
    "artist_name": "Robert Johnson",
    "artist_spotify_url": "https://open.spotify.com/artist/0f8MDDzIc6M4uH1xH0o0gy",
    "album_name": "The George Mitchell Collection Vol. 4",
    "duration_ms": 177200,
    "track_spotify_url": "https://open.spotify.com/track/1LQMedYq9vzeU3hHoij11w"
  },
  {
    "played_at": "2026-04-10T00:55:43.455Z",
    "track_id": "54NsJJUhV364XJyeLl39M5",
    "track_name": "Precious Lord",
    "artist_id": "0f8MDDzIc6M4uH1xH0o0gy",
    "artist_name": "Robert Johnson",
    "artist_spotify_url": "https://open.spotify.com/artist/0f8MDDzIc6M4uH1xH0o0gy",
    "album_name": "The George Mitchell Collection Vol. 4",
    "duration_ms": 119986,
    "track_spotify_url": "https://open.spotify.com/track/54NsJJUhV364XJyeLl39M5"
  },
  {
    "played_at": "2026-04-10T00:53:43.215Z",
    "track_id": "2fiLNDU98eUDqDSiCadnoz",
    "track_name": "I'm a Steady Rollin' Man",
    "artist_id": "0f8MDDzIc6M4uH1xH0o0gy",
    "artist_name": "Robert Johnson",
    "artist_spotify_url": "https://open.spotify.com/artist/0f8MDDzIc6M4uH1xH0o0gy",
    "album_name": "King Of The Delta Blues",
    "duration_ms": 154733,
    "track_spotify_url": "https://open.spotify.com/track/2fiLNDU98eUDqDSiCadnoz"
  },
  {
    "played_at": "2026-04-10T00:51:13.191Z",
    "track_id": "1ypdkO74P92kDAXHnrjaIk",
    "track_name": "Honeymoon Blues",
    "artist_id": "0f8MDDzIc6M4uH1xH0o0gy",
    "artist_name": "Robert Johnson",
    "artist_spotify_url": "https://open.spotify.com/artist/0f8MDDzIc6M4uH1xH0o0gy",
    "album_name": "The Complete Recordings",
    "duration_ms": 135760,
    "track_spotify_url": "https://open.spotify.com/track/1ypdkO74P92kDAXHnrjaIk"
  },
  {
    "played_at": "2026-04-10T00:48:43.302Z",
    "track_id": "5Z4mHJOGAqQr7tMgC6m556",
    "track_name": "Hold My Body Down",
    "artist_id": "0f8MDDzIc6M4uH1xH0o0gy",
    "artist_name": "Robert Johnson",
    "artist_spotify_url": "https://open.spotify.com/artist/0f8MDDzIc6M4uH1xH0o0gy",
    "album_name": "The George Mitchell Collection Vol. 4",
    "duration_ms": 161386,
    "track_spotify_url": "https://open.spotify.com/track/5Z4mHJOGAqQr7tMgC6m556"
  },
  {
    "played_at": "2026-04-10T00:46:13.295Z",
    "track_id": "79VFD8QZFjqbH9V56DimMW",
    "track_name": "From Four Until Late",
    "artist_id": "0f8MDDzIc6M4uH1xH0o0gy",
    "artist_name": "Robert Johnson",
    "artist_spotify_url": "https://open.spotify.com/artist/0f8MDDzIc6M4uH1xH0o0gy",
    "album_name": "King Of The Delta Blues",
    "duration_ms": 142506,
    "track_spotify_url": "https://open.spotify.com/track/79VFD8QZFjqbH9V56DimMW"
  },
  {
    "played_at": "2026-04-10T00:43:43.420Z",
    "track_id": "1tn7gkNr7aAyn91sOK9t4J",
    "track_name": "Drunken Hearted Man - Take 1",
    "artist_id": "0f8MDDzIc6M4uH1xH0o0gy",
    "artist_name": "Robert Johnson",
    "artist_spotify_url": "https://open.spotify.com/artist/0f8MDDzIc6M4uH1xH0o0gy",
    "album_name": "The Complete Recordings",
    "duration_ms": 145733,
    "track_spotify_url": "https://open.spotify.com/track/1tn7gkNr7aAyn91sOK9t4J"
  },
  {
    "played_at": "2026-04-10T00:41:13.270Z",
    "track_id": "1x4iqHqbgf9oHsQJ6FGnCy",
    "track_name": "Lovesick Blues",
    "artist_id": "1FClsNYBUoNFtGgzeG74dW",
    "artist_name": "Hank Williams",
    "artist_spotify_url": "https://open.spotify.com/artist/1FClsNYBUoNFtGgzeG74dW",
    "album_name": "Moanin' The Blues (Expanded Edition)",
    "duration_ms": 165266,
    "track_spotify_url": "https://open.spotify.com/track/1x4iqHqbgf9oHsQJ6FGnCy"
  },
  {
    "played_at": "2026-04-10T00:38:43.091Z",
    "track_id": "6AliaPN7f29wbqun6pFNWX",
    "track_name": "Stop Breakin' Down Blues - Take 1",
    "artist_id": "0f8MDDzIc6M4uH1xH0o0gy",
    "artist_name": "Robert Johnson",
    "artist_spotify_url": "https://open.spotify.com/artist/0f8MDDzIc6M4uH1xH0o0gy",
    "album_name": "King Of The Delta Blues",
    "duration_ms": 135466,
    "track_spotify_url": "https://open.spotify.com/track/6AliaPN7f29wbqun6pFNWX"
  },
  {
    "played_at": "2026-04-10T00:36:13.377Z",
    "track_id": "4xDyRlI0IJEdSe4AELHZcK",
    "track_name": "Little Queen of Spades - Take 1",
    "artist_id": "0f8MDDzIc6M4uH1xH0o0gy",
    "artist_name": "Robert Johnson",
    "artist_spotify_url": "https://open.spotify.com/artist/0f8MDDzIc6M4uH1xH0o0gy",
    "album_name": "The Complete Recordings",
    "duration_ms": 130600,
    "track_spotify_url": "https://open.spotify.com/track/4xDyRlI0IJEdSe4AELHZcK"
  },
  {
    "played_at": "2026-04-10T00:34:13.373Z",
    "track_id": "6st2tGe2XZWvtpYnLOQgp2",
    "track_name": "He'll Make a Way",
    "artist_id": "0f8MDDzIc6M4uH1xH0o0gy",
    "artist_name": "Robert Johnson",
    "artist_spotify_url": "https://open.spotify.com/artist/0f8MDDzIc6M4uH1xH0o0gy",
    "album_name": "The George Mitchell Collection Vol. 4",
    "duration_ms": 196640,
    "track_spotify_url": "https://open.spotify.com/track/6st2tGe2XZWvtpYnLOQgp2"
  },
  {
    "played_at": "2026-04-10T00:30:43.807Z",
    "track_id": "6jFbvFjbFSphuXZVr4xWO5",
    "track_name": "I Believe I'll Dust My Broom",
    "artist_id": "0f8MDDzIc6M4uH1xH0o0gy",
    "artist_name": "Robert Johnson",
    "artist_spotify_url": "https://open.spotify.com/artist/0f8MDDzIc6M4uH1xH0o0gy",
    "album_name": "King Of The Delta Blues",
    "duration_ms": 177200,
    "track_spotify_url": "https://open.spotify.com/track/6jFbvFjbFSphuXZVr4xWO5"
  },
  {
    "played_at": "2026-04-10T00:28:13.308Z",
    "track_id": "2EaZxrfE6L0qyBGCMAxbsM",
    "track_name": "Phonograph Blues - Take 1",
    "artist_id": "0f8MDDzIc6M4uH1xH0o0gy",
    "artist_name": "Robert Johnson",
    "artist_spotify_url": "https://open.spotify.com/artist/0f8MDDzIc6M4uH1xH0o0gy",
    "album_name": "The Complete Recordings",
    "duration_ms": 157960,
    "track_spotify_url": "https://open.spotify.com/track/2EaZxrfE6L0qyBGCMAxbsM"
  },
  {
    "played_at": "2026-04-10T00:24:43.189Z",
    "track_id": "3LrdrGd8Fv3uiJNq9b5wj3",
    "track_name": "Malted Milk",
    "artist_id": "0f8MDDzIc6M4uH1xH0o0gy",
    "artist_name": "Robert Johnson",
    "artist_spotify_url": "https://open.spotify.com/artist/0f8MDDzIc6M4uH1xH0o0gy",
    "album_name": "Martin Scorsese Presents The Blues: Robert Johnson",
    "duration_ms": 140533,
    "track_spotify_url": "https://open.spotify.com/track/3LrdrGd8Fv3uiJNq9b5wj3"
  },
  {
    "played_at": "2026-04-10T00:22:43.197Z",
    "track_id": "5tC9rKaT2tybkuV1FByFJr",
    "track_name": "Dead Shrimp Blues",
    "artist_id": "0f8MDDzIc6M4uH1xH0o0gy",
    "artist_name": "Robert Johnson",
    "artist_spotify_url": "https://open.spotify.com/artist/0f8MDDzIc6M4uH1xH0o0gy",
    "album_name": "The Complete Recordings",
    "duration_ms": 149333,
    "track_spotify_url": "https://open.spotify.com/track/5tC9rKaT2tybkuV1FByFJr"
  },
  {
    "played_at": "2026-04-10T00:20:13.205Z",
    "track_id": "1TrGdXSgiBm8W68D2K1COG",
    "track_name": "Cross Road Blues",
    "artist_id": "0f8MDDzIc6M4uH1xH0o0gy",
    "artist_name": "Robert Johnson",
    "artist_spotify_url": "https://open.spotify.com/artist/0f8MDDzIc6M4uH1xH0o0gy",
    "album_name": "King Of The Delta Blues Singers",
    "duration_ms": 149560,
    "track_spotify_url": "https://open.spotify.com/track/1TrGdXSgiBm8W68D2K1COG"
  },
  {
    "played_at": "2026-04-10T00:17:43.274Z",
    "track_id": "4xzB1THFeAaZeec7NhqW4j",
    "track_name": "Stop Breakin' Down Blues",
    "artist_id": "5BO1F2wBHUCoX02ZdPP23o",
    "artist_name": "Charlie Beale",
    "artist_spotify_url": "https://open.spotify.com/artist/5BO1F2wBHUCoX02ZdPP23o",
    "album_name": "Breakin' Down Blues",
    "duration_ms": 189818,
    "track_spotify_url": "https://open.spotify.com/track/4xzB1THFeAaZeec7NhqW4j"
  },
  {
    "played_at": "2026-04-10T00:14:13.185Z",
    "track_id": "2KkJj006V93x8d9dXpgmIg",
    "track_name": "Hellhound on My Trail",
    "artist_id": "0f8MDDzIc6M4uH1xH0o0gy",
    "artist_name": "Robert Johnson",
    "artist_spotify_url": "https://open.spotify.com/artist/0f8MDDzIc6M4uH1xH0o0gy",
    "album_name": "King Of The Delta Blues",
    "duration_ms": 154466,
    "track_spotify_url": "https://open.spotify.com/track/2KkJj006V93x8d9dXpgmIg"
  },
  {
    "played_at": "2026-04-10T00:11:43.639Z",
    "track_id": "6xvY8RthrKhbkY3lxxH752",
    "track_name": "Love in Vain - Take 1",
    "artist_id": "0f8MDDzIc6M4uH1xH0o0gy",
    "artist_name": "Robert Johnson",
    "artist_spotify_url": "https://open.spotify.com/artist/0f8MDDzIc6M4uH1xH0o0gy",
    "album_name": "King Of The Delta Blues",
    "duration_ms": 143200,
    "track_spotify_url": "https://open.spotify.com/track/6xvY8RthrKhbkY3lxxH752"
  },
  {
    "played_at": "2026-04-10T00:09:13.263Z",
    "track_id": "4RzFnBP0EDGpX9CfUdLTda",
    "track_name": "Walkin' Blues",
    "artist_id": "0f8MDDzIc6M4uH1xH0o0gy",
    "artist_name": "Robert Johnson",
    "artist_spotify_url": "https://open.spotify.com/artist/0f8MDDzIc6M4uH1xH0o0gy",
    "album_name": "King Of The Delta Blues Singers",
    "duration_ms": 150666,
    "track_spotify_url": "https://open.spotify.com/track/4RzFnBP0EDGpX9CfUdLTda"
  },
  {
    "played_at": "2026-04-10T00:06:43.291Z",
    "track_id": "3pS6HIZimRIBMrQU6vRfpp",
    "track_name": "Traveling Riverside Blues",
    "artist_id": "0f8MDDzIc6M4uH1xH0o0gy",
    "artist_name": "Robert Johnson",
    "artist_spotify_url": "https://open.spotify.com/artist/0f8MDDzIc6M4uH1xH0o0gy",
    "album_name": "King Of The Delta Blues Singers",
    "duration_ms": 167666,
    "track_spotify_url": "https://open.spotify.com/track/3pS6HIZimRIBMrQU6vRfpp"
  },
  {
    "played_at": "2026-04-10T00:04:13.340Z",
    "track_id": "4vrPulRxzgljqsYtgGQrpk",
    "track_name": "They're Red Hot - SA.2627-1",
    "artist_id": "0f8MDDzIc6M4uH1xH0o0gy",
    "artist_name": "Robert Johnson",
    "artist_spotify_url": "https://open.spotify.com/artist/0f8MDDzIc6M4uH1xH0o0gy",
    "album_name": "The Centennial Collection",
    "duration_ms": 178853,
    "track_spotify_url": "https://open.spotify.com/track/4vrPulRxzgljqsYtgGQrpk"
  },
  {
    "played_at": "2026-04-10T00:01:13.448Z",
    "track_id": "5xjG7nV5ncQAHkuifsz4v3",
    "track_name": "Hell Hound On My Trail",
    "artist_id": "0f8MDDzIc6M4uH1xH0o0gy",
    "artist_name": "Robert Johnson",
    "artist_spotify_url": "https://open.spotify.com/artist/0f8MDDzIc6M4uH1xH0o0gy",
    "album_name": "King Of The Delta Blues Singers",
    "duration_ms": 157866,
    "track_spotify_url": "https://open.spotify.com/track/5xjG7nV5ncQAHkuifsz4v3"
  },
  {
    "played_at": "2026-04-09T23:58:13.411Z",
    "track_id": "10W125nMbncRGcXRBoACOx",
    "track_name": "Come On In My Kitchen",
    "artist_id": "0f8MDDzIc6M4uH1xH0o0gy",
    "artist_name": "Robert Johnson",
    "artist_spotify_url": "https://open.spotify.com/artist/0f8MDDzIc6M4uH1xH0o0gy",
    "album_name": "King Of The Delta Blues Singers",
    "duration_ms": 172306,
    "track_spotify_url": "https://open.spotify.com/track/10W125nMbncRGcXRBoACOx"
  },
  {
    "played_at": "2026-04-09T23:55:43.122Z",
    "track_id": "2wPHe2ecCdkT0ly0km12g4",
    "track_name": "Sweet Home Chicago",
    "artist_id": "0f8MDDzIc6M4uH1xH0o0gy",
    "artist_name": "Robert Johnson",
    "artist_spotify_url": "https://open.spotify.com/artist/0f8MDDzIc6M4uH1xH0o0gy",
    "album_name": "King Of The Delta Blues",
    "duration_ms": 176626,
    "track_spotify_url": "https://open.spotify.com/track/2wPHe2ecCdkT0ly0km12g4"
  },
  {
    "played_at": "2026-04-09T23:52:43.251Z",
    "track_id": "1QCUrXrY1qlxRhL3a9LYCA",
    "track_name": "Me and the Devil Blues",
    "artist_id": "0f8MDDzIc6M4uH1xH0o0gy",
    "artist_name": "Robert Johnson",
    "artist_spotify_url": "https://open.spotify.com/artist/0f8MDDzIc6M4uH1xH0o0gy",
    "album_name": "King Of The Delta Blues Singers",
    "duration_ms": 154666,
    "track_spotify_url": "https://open.spotify.com/track/1QCUrXrY1qlxRhL3a9LYCA"
  },
  {
    "played_at": "2026-04-09T23:50:13.218Z",
    "track_id": "2t6BfB8I8NReNCHPOVY8qI",
    "track_name": "Cross Road Blues - Take 2",
    "artist_id": "0f8MDDzIc6M4uH1xH0o0gy",
    "artist_name": "Robert Johnson",
    "artist_spotify_url": "https://open.spotify.com/artist/0f8MDDzIc6M4uH1xH0o0gy",
    "album_name": "The Complete Recordings",
    "duration_ms": 147000,
    "track_spotify_url": "https://open.spotify.com/track/2t6BfB8I8NReNCHPOVY8qI"
  },
  {
    "played_at": "2026-04-08T00:05:46.820Z",
    "track_id": "3iqx4tspx1kHszlZavYv8E",
    "track_name": "Whole Earth Chant",
    "artist_id": "4ZmNj7bRSU3YCtH0oaJSef",
    "artist_name": "Paul Winter",
    "artist_spotify_url": "https://open.spotify.com/artist/4ZmNj7bRSU3YCtH0oaJSef",
    "album_name": "Winter Consort - Icarus",
    "duration_ms": 460360,
    "track_spotify_url": "https://open.spotify.com/track/3iqx4tspx1kHszlZavYv8E"
  },
  {
    "played_at": "2026-04-07T16:16:53.896Z",
    "track_id": "6O8Gzl2hF55dwr2YXcq2N5",
    "track_name": "Juniper Bear",
    "artist_id": "4ZmNj7bRSU3YCtH0oaJSef",
    "artist_name": "Paul Winter",
    "artist_spotify_url": "https://open.spotify.com/artist/4ZmNj7bRSU3YCtH0oaJSef",
    "album_name": "Winter Consort - Icarus",
    "duration_ms": 184533,
    "track_spotify_url": "https://open.spotify.com/track/6O8Gzl2hF55dwr2YXcq2N5"
  },
  {
    "played_at": "2026-04-07T16:13:54.961Z",
    "track_id": "5QssnLt3a4UjcG4OB5GbIT",
    "track_name": "Sunwheel",
    "artist_id": "4ZmNj7bRSU3YCtH0oaJSef",
    "artist_name": "Paul Winter",
    "artist_spotify_url": "https://open.spotify.com/artist/4ZmNj7bRSU3YCtH0oaJSef",
    "album_name": "Winter Consort - Icarus",
    "duration_ms": 280560,
    "track_spotify_url": "https://open.spotify.com/track/5QssnLt3a4UjcG4OB5GbIT"
  },
  {
    "played_at": "2026-04-07T16:09:24.185Z",
    "track_id": "3n3nOtAyIbrQcErt2M9WAX",
    "track_name": "The Silence of a Candle",
    "artist_id": "4ZmNj7bRSU3YCtH0oaJSef",
    "artist_name": "Paul Winter",
    "artist_spotify_url": "https://open.spotify.com/artist/4ZmNj7bRSU3YCtH0oaJSef",
    "album_name": "Winter Consort - Icarus",
    "duration_ms": 204893,
    "track_spotify_url": "https://open.spotify.com/track/3n3nOtAyIbrQcErt2M9WAX"
  },
  {
    "played_at": "2026-04-07T16:05:55.617Z",
    "track_id": "5YZV5HJFFfWgwWNW28oPSV",
    "track_name": "Ode to a Fillmore Dressing Room",
    "artist_id": "4ZmNj7bRSU3YCtH0oaJSef",
    "artist_name": "Paul Winter",
    "artist_spotify_url": "https://open.spotify.com/artist/4ZmNj7bRSU3YCtH0oaJSef",
    "album_name": "Winter Consort - Icarus",
    "duration_ms": 332106,
    "track_spotify_url": "https://open.spotify.com/track/5YZV5HJFFfWgwWNW28oPSV"
  },
  {
    "played_at": "2026-04-07T16:00:24.424Z",
    "track_id": "6At2I2Dkw4674fN3j9lk2H",
    "track_name": "Icarus",
    "artist_id": "4ZmNj7bRSU3YCtH0oaJSef",
    "artist_name": "Paul Winter",
    "artist_spotify_url": "https://open.spotify.com/artist/4ZmNj7bRSU3YCtH0oaJSef",
    "album_name": "Winter Consort - Icarus",
    "duration_ms": 181400,
    "track_spotify_url": "https://open.spotify.com/track/6At2I2Dkw4674fN3j9lk2H"
  }
]